ndx_binned_spikes/spec/ndx-binned-spikes.extensions.yaml
ndx_binned_spikes/spec/ndx-binned-spikes.namespace.yaml
ndx_binned_spikes/__init__.py
ndx_binned_spikes/testing/__init__.py
ndx_binned_spikes/testing/mock.py
ndx_binned_spikes-0.3.1.dist-info/METADATA
ndx_binned_spikes-0.3.1.dist-info/WHEEL
ndx_binned_spikes-0.3.1.dist-info/licenses/LICENSE.txt
ndx_binned_spikes-0.3.1.dist-info/RECORD
