Metadata-Version: 2.4
Name: ndx-binned-spikes
Version: 0.3.1
Summary: NWB extension for storing binned spike data
Project-URL: Homepage, https://github.com/catalystneuro/ndx-binned-spikes
Project-URL: Documentation, https://github.com/catalystneuro/ndx-binned-spikes
Project-URL: Bug Tracker, https://github.com/catalystneuro/ndx-binned-spikes/issues
Project-URL: Discussions, https://github.com/catalystneuro/ndx-binned-spikes/discussions
Project-URL: Changelog, https://github.com/catalystneuro/ndx-binned-spikes/blob/main/CHANGELOG.md
Author-email: Ben Dicther <ben.dichter@gmail.com>, Heberto Mayorquin <h.mayorquin@gmail.com>
License: MIT
License-File: LICENSE.txt
Keywords: NWB,NeurodataWithoutBorders,ndx-extension,nwb-extension
Classifier: Development Status :: 3 - Alpha
Classifier: Intended Audience :: Developers
Classifier: Intended Audience :: Science/Research
Classifier: License :: OSI Approved :: MIT License
Classifier: Operating System :: OS Independent
Classifier: Programming Language :: Python :: 3.10
Classifier: Programming Language :: Python :: 3.11
Classifier: Programming Language :: Python :: 3.12
Classifier: Programming Language :: Python :: 3.13
Requires-Python: >=3.10
Requires-Dist: hdmf>=4.0.0
Requires-Dist: pynwb>=3.0.0
